Metadata-Version: 2.1
Name: odoo-addon-partner_code_program_territory_hide_pdf_fields
Version: 18.0.1.0.0
Requires-Python: >=3.10
Requires-Dist: odoo-addon-partner_address_hide_pdf_fields==18.0.*
Requires-Dist: odoo-addon-partner_code_program_territory==18.0.*
Requires-Dist: odoo==18.0.*
Summary: Hide the partner code program territory fields from PDFs
Home-page: https://github.com/sygel-technology/sy-partner-contact
License: AGPL-3
Author: Sygel
Classifier: Programming Language :: Python
Classifier: Framework :: Odoo
Classifier: Framework :: Odoo :: 18.0
Classifier: License :: OSI Approved :: GNU Affero General Public License v3
